shallow/__init__.py
shallow/utils.py
shallow/jax/__init__.py
shallow/jax/flows.py
shallow/jax/nets.py
shallow/jax/train.py
shallow/jax/transforms.py
shallow/jax/utils.py
shallow/numpyro/__init__.py
shallow/pyro/__init__.py
shallow/pyro/pyro.py
shallow/tensorflow/__init__.py
shallow/tensorflow/tensorflow.py
shallow/tensorflow/transform.py
shallow/tensorflow/utils.py
shallow/torch/__init__.py
shallow/torch/flows.py
shallow/torch/nets.py
shallow/torch/training.py
shallow/torch/utils.py
shallow-0.3.dist-info/LICENSE
shallow-0.3.dist-info/METADATA
shallow-0.3.dist-info/WHEEL
shallow-0.3.dist-info/top_level.txt
shallow-0.3.dist-info/RECORD
