Metadata-Version: 2.1
Name: shallow
Version: 0.3
Summary: shallow
Home-page: https://github.com/mdmould/shallow
Author: Matthew Mould
Author-email: mattdmould@gmail.com
License: MIT
Requires-Python: >=3.10
License-File: LICENSE
Requires-Dist: numpy
Requires-Dist: tqdm
